{
  "alumnos": [
    {
      "id": 1,
      "nombre": "Leonardo Jara",
      "seccion": "PGY4121-004D",
      "fecha": "22/10/2023"
    },
    {
      "id": 2,
      "nombre": "Matias Lemus",
      "seccion": "PGY4121-004D",
      "fecha": "22/10/2023"
    },
    {
      "nombre": "Gustavo Hermosilla",
      "seccion": "PGY4121-004D",
      "fecha": "22/10/2023",
      "id": 3
    },
    {
      "nombre": "Esteban Gonzales",
      "seccion": "PGY4121-004D",
      "fecha": "22/10/2023",
      "id": 4
    },
    {
      "nombre": "Daniel Jara",
      "seccion": "PGY4121-004D",
      "fecha": "22/10/2023",
      "id": 5
    }
  ]
}